{
  "id": "f1b1c938-ec63-42d4-a452-acd4a71ffdc7",
  "batch_id": "557ad67e-f880-4068-a268-ba4070c7cbfe",
  "url": "https://youtu.be/uBWuKh1nZ2Y?is=qts27fzvHXXrDxAP",
  "title": null,
  "note": null,
  "tags": [],
  "category": null,
  "source": "discord",
  "created_at": "2026-03-29T10:27:36.345Z",
  "discord": {
    "guild_id": "1026842752232734811",
    "channel_id": "1449479522993836213",
    "message_id": "1487760129204949012",
    "author_id": "894581215720529961",
    "author_username": "bertrand0824",
    "message_url": "https://discord.com/channels/1026842752232734811/1449479522993836213/1487760129204949012"
  }
}