{
  "id": "2485724b-37a3-480a-a6f2-903d25ba8d81",
  "batch_id": "5f86637e-2c6e-4194-bf78-b27adcaf35ee",
  "url": "https://www.reddit.com/r/cursor/s/FSUaF8wzpz",
  "title": null,
  "note": null,
  "tags": [],
  "category": null,
  "source": "discord",
  "created_at": "2025-12-14T00:52:26.426Z",
  "discord": {
    "guild_id": "1026842752232734811",
    "channel_id": "1449479522993836213",
    "message_id": "1449564658460786885",
    "author_id": "894581215720529961",
    "author_username": "bertrand0824",
    "message_url": "https://discord.com/channels/1026842752232734811/1449479522993836213/1449564658460786885"
  }
}